dynamic_pydantic/__init__.py
dynamic_pydantic-0.1.1.dist-info/METADATA
dynamic_pydantic-0.1.1.dist-info/WHEEL
dynamic_pydantic-0.1.1.dist-info/top_level.txt
dynamic_pydantic-0.1.1.dist-info/RECORD
