Metadata-Version: 2.1
Name: dynamic-pydantic
Version: 0.1.1
Summary: Dynamic Pydantic is the easiest way to create and validate AI agent tools and databases.
Author-email: Luka <luka@lukafilipovic.com>
License: MIT License
Project-URL: Repository, https://github.com/lukafilipxvic/dynamic-pydantic
Project-URL: Changelog, https://github.com/lukafilipxvic/dynamic-pydantic/blob/main/CHANGELOG.md
Project-URL: Releases, https://github.com/lukafilipxvic/dynamic-pydantic/releases
Keywords: instructor,pydantic,AI Agents
Requires-Python: >=3.10
Requires-Dist: instructor
Requires-Dist: litellm
Requires-Dist: pydantic>=2.0.0
Provides-Extra: examples
Requires-Dist: stealth-requests[parsers]; extra == "examples"
Requires-Dist: pydantic-ai; extra == "examples"
Requires-Dist: pymupdf4llm; extra == "examples"
